banyarag/__init__.py
banyarag/banyainstance.py
banyarag/file_uploader.py
banyarag-0.1.31.dist-info/METADATA
banyarag-0.1.31.dist-info/WHEEL
banyarag-0.1.31.dist-info/top_level.txt
banyarag-0.1.31.dist-info/RECORD
