Metadata-Version: 2.1
Name: banyarag
Version: 0.1.31
Summary: Banya RAG file uploader and training library
Home-page: https://github.com/DaiosFoundations/banyarag
Author: smkim
Author-email: ksm@daiblab.com
Classifier: Programming Language :: Python :: 3
Classifier: License :: OSI Approved :: MIT License
Classifier: Operating System :: OS Independent
Requires-Python: >=3.10
Requires-Dist: requests
